chaokai/__init__.py
chaokai/crypto/__init__.py
chaokai/crypto/aes.py
chaokai/crypto/des.py
chaokai/crypto/hash.py
chaokai/crypto/rsa.py
chaokai/sms/__init__.py
chaokai/sms/aliyun.py
chaokai/uni/__init__.py
chaokai/uni/date.py
chaokai/uni/idcard.py
chaokai/uni/money.py
chaokai/uni/uid.py
chaokai-0.0.14.dist-info/METADATA
chaokai-0.0.14.dist-info/WHEEL
chaokai-0.0.14.dist-info/RECORD
