Metadata-Version: 2.4
Name: chaokai
Version: 0.0.14
Summary: 
Requires-Python: >=3.9,<4.0
Classifier: Programming Language :: Python :: 3
Classifier: Programming Language :: Python :: 3.9
Classifier: Programming Language :: Python :: 3.10
Classifier: Programming Language :: Python :: 3.11
Classifier: Programming Language :: Python :: 3.12
Classifier: Programming Language :: Python :: 3.13
Classifier: Programming Language :: Python :: 3.14
Requires-Dist: pycryptodomex (>=3.23.0,<4.0.0)
Requires-Dist: requests (>=2.32.3,<3.0.0)
